pylog2pdf/__init__.py
pylog2pdf/logger.py
pylog2pdf/pdf_io.py
pylog2pdf-0.1.0.dist-info/LICENSE
pylog2pdf-0.1.0.dist-info/WHEEL
pylog2pdf-0.1.0.dist-info/METADATA
pylog2pdf-0.1.0.dist-info/RECORD
