Metadata-Version: 2.1
Name: pylog2pdf
Version: 0.1.0
Summary: PDF, a visualisation of your calculation, can have essentials of your code.
Home-page: https://github.com/KaoruNishikawa/PyLog2PDF
License: MIT
Author: KaoruNishikawa
Author-email: k.nishikawa@a.phys.nagoya-u.ac.jp
Requires-Python: >=3.6,<4.0
Classifier: License :: OSI Approved :: MIT License
Classifier: Programming Language :: Python :: 3
Classifier: Programming Language :: Python :: 3.10
Classifier: Programming Language :: Python :: 3.6
Classifier: Programming Language :: Python :: 3.7
Classifier: Programming Language :: Python :: 3.8
Classifier: Programming Language :: Python :: 3.9
Requires-Dist: PyPDF2 (>=1.24.0,<2.0.0)
Project-URL: Repository, https://github.com/KaoruNishikawa/PyLog2PDF
